<!--
    API Monitor Definitions
    (c) 2011, Rohitab Batra <rohitab@rohitab.com>
    http://www.rohitab.com/apimonitor/
-->
<ApiMonitor>
    <Include Filename="Headers\dwrite.h.xml" />
    <Include Filename="Interfaces\IUnknown.xml" />
    <Interface Name="IDWriteTextFormat" Id="{9c906818-31d7-4fd3-a151-7c5e225db55a}" BaseInterface="IUnknown" OnlineHelp="MSDN" ErrorFunc="HRESULT" Category="Graphics and Gaming/DirectX Graphics and Gaming/DirectWrite">
        <!-- Variables -->
        <!-- Methods -->
        <Api Name="SetTextAlignment">
            <Param Type="DWRITE_TEXT_ALIGNMENT" Name="textAlignment" />
            <Return Type="HRESULT" />
        </Api>
        <Api Name="SetParagraphAlignment">
            <Param Type="DWRITE_PARAGRAPH_ALIGNMENT" Name="paragraphAlignment" />
            <Return Type="HRESULT" />
        </Api>
        <Api Name="SetWordWrapping">
            <Param Type="DWRITE_WORD_WRAPPING" Name="wordWrapping" />
            <Return Type="HRESULT" />
        </Api>
        <Api Name="SetReadingDirection">
            <Param Type="DWRITE_READING_DIRECTION" Name="readingDirection" />
            <Return Type="HRESULT" />
        </Api>
        <Api Name="SetFlowDirection">
            <Param Type="DWRITE_FLOW_DIRECTION" Name="flowDirection" />
            <Return Type="HRESULT" />
        </Api>
        <Api Name="SetIncrementalTabStop">
            <Param Type="FLOAT" Name="incrementalTabStop" />
            <Return Type="HRESULT" />
        </Api>
        <Api Name="SetTrimming">
            <Param Type="DWRITE_TRIMMING const*" Name="trimmingOptions" />
            <Param Type="IDWriteInlineObject*" Name="trimmingSign" />
            <Return Type="HRESULT" />
        </Api>
        <Api Name="SetLineSpacing">
            <Param Type="DWRITE_LINE_SPACING_METHOD" Name="lineSpacingMethod" />
            <Param Type="FLOAT" Name="lineSpacing" />
            <Param Type="FLOAT" Name="baseline" />
            <Return Type="HRESULT" />
        </Api>
        <Api Name="GetTextAlignment">
            <Return Type="DWRITE_TEXT_ALIGNMENT" />
        </Api>
        <Api Name="GetParagraphAlignment">
            <Return Type="DWRITE_PARAGRAPH_ALIGNMENT" />
        </Api>
        <Api Name="GetWordWrapping">
            <Return Type="DWRITE_WORD_WRAPPING" />
        </Api>
        <Api Name="GetReadingDirection">
            <Return Type="DWRITE_READING_DIRECTION" />
        </Api>
        <Api Name="GetFlowDirection">
            <Return Type="DWRITE_FLOW_DIRECTION" />
        </Api>
        <Api Name="GetIncrementalTabStop">
            <Return Type="FLOAT" />
        </Api>
        <Api Name="GetTrimming">
            <Param Type="DWRITE_TRIMMING*" Name="trimmingOptions" />
            <Param Type="IDWriteInlineObject**" Name="trimmingSign" />
            <Return Type="HRESULT" />
        </Api>
        <Api Name="GetLineSpacing">
            <Param Type="DWRITE_LINE_SPACING_METHOD*" Name="lineSpacingMethod" />
            <Param Type="FLOAT*" Name="lineSpacing" />
            <Param Type="FLOAT*" Name="baseline" />
            <Return Type="HRESULT" />
        </Api>
        <Api Name="GetFontCollection">
            <Param Type="IDWriteFontCollection**" Name="fontCollection" />
            <Return Type="HRESULT" />
        </Api>
        <Api Name="GetFontFamilyNameLength">
            <Return Type="UINT32" />
            <Success Return="NotEqual" Value="0" />
        </Api>
        <Api Name="GetFontFamilyName">
            <Param Type="WCHAR*" Name="fontFamilyName" OutputOnly="True" />
            <Param Type="UINT32" Name="nameSize" />
            <Return Type="HRESULT" />
        </Api>
        <Api Name="GetFontWeight">
            <Return Type="DWRITE_FONT_WEIGHT" />
        </Api>
        <Api Name="GetFontStyle">
            <Return Type="DWRITE_FONT_STYLE" />
        </Api>
        <Api Name="GetFontStretch">
            <Return Type="DWRITE_FONT_STRETCH" />
        </Api>
        <Api Name="GetFontSize">
            <Return Type="FLOAT" />
        </Api>
        <Api Name="GetLocaleNameLength">
            <Return Type="UINT32" />
        </Api>
        <Api Name="GetLocaleName">
            <Param Type="WCHAR*" Name="localeName" OutputOnly="True" />
            <Param Type="UINT32" Name="nameSize" />
            <Return Type="HRESULT" />
        </Api>
    </Interface>
</ApiMonitor>
