<!--
    API Monitor Definitions
    (c) 2012, Rohitab Batra <rohitab@rohitab.com>
    http://www.rohitab.com/apimonitor/
-->
<ApiMonitor>
    <Include Filename="Interfaces\Direct2D\Direct2D.h.xml" />
    <Include Filename="Interfaces\Direct2D\ID2D1ConcreteTransform.xml" />
    <Interface Name="ID2D1BlendTransform" Id="{63ac0b32-ba44-450f-8806-7f4ca1ff2f1b}" BaseInterface="ID2D1ConcreteTransform" OnlineHelp="MSDN" ErrorFunc="HRESULT" Category="Graphics and Gaming/DirectX Graphics and Gaming/Direct2D">
        <Api Name="SetDescription">
            <Param Type="CONST D2D1_BLEND_DESCRIPTION*" Name="description" />
            <Return Type="void" />
        </Api>
        <Api Name="GetDescription">
            <Param Type="D2D1_BLEND_DESCRIPTION*" Name="description" />
            <Return Type="void" />
        </Api>
    </Interface>
</ApiMonitor>
