<!--
    API Monitor Definitions
    (c) 2011, Rohitab Batra <rohitab@rohitab.com>
    http://www.rohitab.com/apimonitor/
-->
<ApiMonitor>
    <Include Filename="Interfaces\IUnknown.xml" />
    <Interface Name="IDebugOutputCallbacksWide" Id="{4c7fd663-c394-4e26-8ef1-34ad5ed3764c}" BaseInterface="IUnknown" OnlineHelp="MSDN" ErrorFunc="HRESULT" Category="Diagnostics/Debugging Tools for Windows/Debugger Engine/Callback COM Interfaces">
        <!-- Variables -->
        <!-- Methods -->
        <Api Name="Output">
            <Param Type="[DEBUG_OUTPUT_FLAGS]" Name="Mask" />
            <Param Type="PCWSTR" Name="Text" />
            <Return Type="HRESULT" />
        </Api>
    </Interface>
</ApiMonitor>
