<!--
    API Monitor Definitions
    (c) 2011, Rohitab Batra <rohitab@rohitab.com>
    http://www.rohitab.com/apimonitor/
-->
<ApiMonitor>
    <Include Filename="Interfaces\IUnknown.xml" />
    <Include Filename="Interfaces\WindowsSync\WinSync.h.xml" />
    <Interface Name="ISyncChangeUnit" Id="{60edd8ca-7341-4bb7-95ce-fab6394b51cb}" BaseInterface="IUnknown" OnlineHelp="MSDN" ErrorFunc="HRESULT" Category="Data Access and Storage/Windows Sync">
        <Api Name="GetItemChange">
            <Param Type="ISyncChange**" Name="ppSyncChange" />
            <Return Type="HRESULT" />
        </Api>
        <Api Name="GetChangeUnitId">
            <Param Type="BYTE*" Name="pbChangeUnitId" />
            <Param Type="DWORD*" Name="pcbIdSize" />
            <Return Type="HRESULT" />
        </Api>
        <Api Name="GetChangeUnitVersion">
            <Param Type="const BYTE*" Name="pbCurrentReplicaId" />
            <Param Type="SYNC_VERSION*" Name="pVersion" />
            <Return Type="HRESULT" />
        </Api>
    </Interface>
</ApiMonitor>
