<!--
    API Monitor Definitions
    (c) 2011, Rohitab Batra <rohitab@rohitab.com>
    http://www.rohitab.com/apimonitor/
-->
<ApiMonitor>
    <Include Filename="MMF\mmfdefs.h.xml" />
    <Include Filename="Interfaces\IUnknown.xml" />
    <Interface Name="IDirect3DDeviceManager9" Id="{a0cade0f-06d5-4cf4-a1c7-f3cdd725aa75}" BaseInterface="IUnknown" OnlineHelp="MSDN" ErrorFunc="HRESULT" Category="Audio and Video/Microsoft Media Foundation/Interfaces">
        <Api Name="ResetDevice">
            <Param Type="IDirect3DDevice9*" Name="pDevice" />
            <Param Type="UINT" Name="resetToken" />
            <Return Type="HRESULT" />
        </Api>
        <Api Name="OpenDeviceHandle">
            <Param Type="HANDLE*" Name="phDevice" />
            <Return Type="HRESULT" />
        </Api>
        <Api Name="CloseDeviceHandle">
            <Param Type="HANDLE" Name="hDevice" />
            <Return Type="HRESULT" />
        </Api>
        <Api Name="TestDevice">
            <Param Type="HANDLE" Name="hDevice" />
            <Return Type="HRESULT" />
        </Api>
        <Api Name="LockDevice">
            <Param Type="HANDLE" Name="hDevice" />
            <Param Type="IDirect3DDevice9**" Name="ppDevice" />
            <Param Type="BOOL" Name="fBlock" />
            <Return Type="HRESULT" />
        </Api>
        <Api Name="UnlockDevice">
            <Param Type="HANDLE" Name="hDevice" />
            <Param Type="BOOL" Name="fSaveState" />
            <Return Type="HRESULT" />
        </Api>
        <Api Name="GetVideoService">
            <Param Type="HANDLE" Name="hDevice" />
            <Param Type="REFIID" Name="riid" />
            <Param Type="void**" Name="ppService" InterfaceId="riid" />
            <Return Type="HRESULT" />
        </Api>
    </Interface>
</ApiMonitor>
