<!--
    API Monitor Definitions
    (c) 2011, Rohitab Batra <rohitab@rohitab.com>
    http://www.rohitab.com/apimonitor/
-->
<ApiMonitor>
    <Include Filename="MMF\mmfdefs.h.xml" />
    <Include Filename="Interfaces\IUnknown.xml" />
    <Interface Name="IMFMediaTypeHandler" Id="{e93dcf6c-4b07-4e1e-8123-aa16ed6eadf5}" BaseInterface="IUnknown" OnlineHelp="MSDN" ErrorFunc="HRESULT" Category="Audio and Video/Microsoft Media Foundation/Interfaces">
        <Api Name="IsMediaTypeSupported">
            <Param Type="IMFMediaType*" Name="pMediaType" />
            <Param Type="IMFMediaType**" Name="ppMediaType" />
            <Return Type="HRESULT" />
        </Api>
        <Api Name="GetMediaTypeCount">
            <Param Type="DWORD*" Name="pdwTypeCount" />
            <Return Type="HRESULT" />
        </Api>
        <Api Name="GetMediaTypeByIndex">
            <Param Type="DWORD" Name="dwIndex" />
            <Param Type="IMFMediaType**" Name="ppType" />
            <Return Type="HRESULT" />
        </Api>
        <Api Name="SetCurrentMediaType">
            <Param Type="IMFMediaType*" Name="pMediaType" />
            <Return Type="HRESULT" />
        </Api>
        <Api Name="GetCurrentMediaType">
            <Param Type="IMFMediaType**" Name="ppMediaType" />
            <Return Type="HRESULT" />
        </Api>
        <Api Name="GetMajorType">
            <Param Type="GUID*" Name="pguidMajorType" />
            <Return Type="HRESULT" />
        </Api>
    </Interface>
</ApiMonitor>
